dric/__init__.py
dric/client.py
dric/dataset.py
dric/dric_pb2.py
dric/dric_pb2_grpc.py
dric/dric_types.py
dric/marmot_dataset_pb2.py
dric/marmot_dataset_pb2_grpc.py
dric/marmot_file_pb2.py
dric/marmot_file_pb2_grpc.py
dric/marmot_type_pb2.py
dric/marmot_type_pb2_grpc.py
dric/mqtt.py
dric/proto_utils.py
dric/types.py
dric/utils.py
dric_client-1.1.2.dist-info/METADATA
dric_client-1.1.2.dist-info/WHEEL
dric_client-1.1.2.dist-info/top_level.txt
dric_client-1.1.2.dist-info/RECORD
